LICENSE
MANIFEST.in
README.rst
setup.py
stlsort.py
stlsort.egg-info/PKG-INFO
stlsort.egg-info/SOURCES.txt
stlsort.egg-info/dependency_links.txt
stlsort.egg-info/entry_points.txt
stlsort.egg-info/top_level.txt