Metadata-Version: 1.1
Name: stlsort
Version: 0.0.3
Summary: Sort ASCII STL files for better version control
Home-page: https://github.com/hroncok/stlsort
Author: Miro Hrončok
Author-email: miro@hroncok.cz
License: GPLv2
Keywords: STL,mesh,3D,sort,git
Platform: UNKNOWN
Classifier: Development Status :: 3 - Alpha
Classifier: License :: OSI Approved :: GNU General Public License v2 (GPLv2)
Classifier: Operating System :: POSIX :: Linux
Classifier: Programming Language :: Python
Classifier: Programming Language :: Python :: 2
Classifier: Programming Language :: Python :: 3
